mldrop_client/__init__.py
mldrop_client/client.py
mldrop_client/domain.py
mldrop_client/common/__init__.py
mldrop_client/common/http_client.py
mldrop_client/common/utils.py
mldrop_client/tf/__init__.py
mldrop_client/tf/test_tf_models.py
mldrop_client/tf/tf_stuff.py
mldrop_client-0.1.1.dist-info/METADATA
mldrop_client-0.1.1.dist-info/WHEEL
mldrop_client-0.1.1.dist-info/top_level.txt
mldrop_client-0.1.1.dist-info/RECORD
